async_pjsekai/api.py
async_pjsekai/asset.py
async_pjsekai/asset_bundle.py
async_pjsekai/client.py
async_pjsekai/enums/enums.py
async_pjsekai/enums/information.py
async_pjsekai/enums/platform.py
async_pjsekai/enums/tutorial_status.py
async_pjsekai/enums/unknown.py
async_pjsekai/exceptions.py
async_pjsekai/live.py
async_pjsekai/models/asset_bundle_info.py
async_pjsekai/models/converters.py
async_pjsekai/models/game_version.py
async_pjsekai/models/information.py
async_pjsekai/models/master_data.py
async_pjsekai/models/system_info.py
async_pjsekai/utilities.py
async_pjsekai-0.0.10.dev2.dist-info/METADATA
async_pjsekai-0.0.10.dev2.dist-info/WHEEL
async_pjsekai-0.0.10.dev2.dist-info/RECORD
